resilion/__init__.py
resilion/config.py
resilion/core.py
resilion-0.0.1.dist-info/licenses/LICENSE
resilion-0.0.1.dist-info/METADATA
resilion-0.0.1.dist-info/WHEEL
resilion-0.0.1.dist-info/top_level.txt
resilion-0.0.1.dist-info/RECORD
