Metadata-Version: 2.4
Name: resilion
Version: 0.0.1
Summary: Mission resilience modeling framework (space systems first; extensible to humans, infra, edge)
Author: HexaF Innovations LLC
License: MIT
Project-URL: Homepage, https://github.com/hexaf-innovations/resilion
Project-URL: Repository, https://github.com/hexaf-innovations/resilion
Classifier: Development Status :: 2 - Pre-Alpha
Classifier: Intended Audience :: Science/Research
Classifier: Topic :: Scientific/Engineering :: Physics
Classifier: Topic :: Scientific/Engineering :: Artificial Intelligence
Classifier: Programming Language :: Python :: 3
Classifier: Programming Language :: Python :: 3 :: Only
Requires-Python: >=3.10
License-File: LICENSE
Dynamic: license-file
